mckit_meshes/__init__.py
mckit_meshes/cli/__init__.py
mckit_meshes/cli/commands/__init__.py
mckit_meshes/cli/commands/addnpz.py
mckit_meshes/cli/commands/mesh2npz.py
mckit_meshes/cli/commands/npz2vtk.py
mckit_meshes/cli/logging_setup.py
mckit_meshes/cli/runner.py
mckit_meshes/fmesh.py
mckit_meshes/m_file_iterator.py
mckit_meshes/mesh/__init__.py
mckit_meshes/mesh/geometry_spec.py
mckit_meshes/mesh2com.py
mckit_meshes/particle_kind.py
mckit_meshes/py.typed
mckit_meshes/utils/__init__.py
mckit_meshes/utils/_io.py
mckit_meshes/utils/cartesian_product.py
mckit_meshes/utils/rebin.py
mckit_meshes/utils/testing.py
mckit_meshes/version.py
mckit_meshes/wgtmesh.py
mckit_meshes-0.2.0.dist-info/LICENSE
mckit_meshes-0.2.0.dist-info/METADATA
mckit_meshes-0.2.0.dist-info/WHEEL
mckit_meshes-0.2.0.dist-info/entry_points.txt
mckit_meshes-0.2.0.dist-info/RECORD
