Metadata-Version: 2.3
Name: mckit-meshes
Version: 0.2.0
Summary: Python tools to work with MCNP meshtallies and weight meshes.
License: MIT
Keywords: MCNP,mesh,weights,variance reduction
Author: dvp2015
Author-email: dmitri_portnov@yahoo.com
Requires-Python: >=3.10,<3.14
Classifier: Development Status :: 4 - Beta
Classifier: Environment :: Console
Classifier: Intended Audience :: Developers
Classifier: Intended Audience :: Science/Research
Classifier: License :: OSI Approved :: MIT License
Classifier: Operating System :: OS Independent
Classifier: Programming Language :: Python :: 3
Classifier: Programming Language :: Python :: 3.10
Classifier: Programming Language :: Python :: 3.11
Classifier: Programming Language :: Python :: 3.12
Classifier: Programming Language :: Python :: 3.13
Classifier: Topic :: Scientific/Engineering :: Physics
Requires-Dist: click (>=8.0.1)
Requires-Dist: loguru (>=0.6.0)
Requires-Dist: numpy (>=2.1.3)
Requires-Dist: pyevtk (>=1.4.1)
Requires-Dist: toolz (>=0.11.2)
Project-URL: Changelog, https://github.com/MC-kit/mckit-meshes/releases
Project-URL: Homepage, https://github.com/MC-kit/mckit-meshes
Project-URL: Repository, https://github.com/MC-kit/mckit-meshes
